google/api/annotations.proto
google/api/annotations_pb2.py
google/api/auth.proto
google/api/auth_pb2.py
google/api/backend.proto
google/api/backend_pb2.py
google/api/billing.proto
google/api/billing_pb2.py
google/api/client.proto
google/api/client_pb2.py
google/api/config_change.proto
google/api/config_change_pb2.py
google/api/consumer.proto
google/api/consumer_pb2.py
google/api/context.proto
google/api/context_pb2.py
google/api/control.proto
google/api/control_pb2.py
google/api/distribution.proto
google/api/distribution_pb2.py
google/api/documentation.proto
google/api/documentation_pb2.py
google/api/endpoint.proto
google/api/endpoint_pb2.py
google/api/error_reason.proto
google/api/error_reason_pb2.py
google/api/field_behavior.proto
google/api/field_behavior_pb2.py
google/api/field_info.proto
google/api/field_info_pb2.py
google/api/http.proto
google/api/http_pb2.py
google/api/httpbody.proto
google/api/httpbody_pb2.py
google/api/label.proto
google/api/label_pb2.py
google/api/launch_stage.proto
google/api/launch_stage_pb2.py
google/api/log.proto
google/api/log_pb2.py
google/api/logging.proto
google/api/logging_pb2.py
google/api/metric.proto
google/api/metric_pb2.py
google/api/monitored_resource.proto
google/api/monitored_resource_pb2.py
google/api/monitoring.proto
google/api/monitoring_pb2.py
google/api/policy.proto
google/api/policy_pb2.py
google/api/quota.proto
google/api/quota_pb2.py
google/api/resource.proto
google/api/resource_pb2.py
google/api/routing.proto
google/api/routing_pb2.py
google/api/service.proto
google/api/service_pb2.py
google/api/source_info.proto
google/api/source_info_pb2.py
google/api/system_parameter.proto
google/api/system_parameter_pb2.py
google/api/usage.proto
google/api/usage_pb2.py
google/api/visibility.proto
google/api/visibility_pb2.py
google/cloud/extended_operations.proto
google/cloud/extended_operations_pb2.py
google/cloud/location/locations.proto
google/cloud/location/locations_pb2.py
google/gapic/metadata/gapic_metadata.proto
googleapis_common_protos-1.64.0.dist-info/LICENSE
googleapis_common_protos-1.64.0.dist-info/METADATA
googleapis_common_protos-1.64.0.dist-info/WHEEL
googleapis_common_protos-1.64.0.dist-info/top_level.txt
googleapis_common_protos-1.64.0.dist-info/RECORD
